chemexp/__init__.py
chemexp/__main__.py
chemexp/chemprop_lime.py
chemexp/chemprop_path_explain.py
chemexp/explained_mol_graph.py
chemexp/explainer_utils.py
chemexp/path_explainer_torch.py
chemexp/server.py
chemexp/static/arrow.svg
chemexp/static/colormap.png
chemexp/static/footer1.svg
chemexp/static/footer2.svg
chemexp/static/pill.png
chemexp/static/pill_add.png
chemexp/static/selectbox.css
chemexp/static/smiles_error.png
chemexp/static/smiles_error_rect.png
chemexp/static/style.css
chemexp/templates/display.html
chemexp/templates/index.html
chemexp/templates/interactions.html
chemexp/templates/results.html
chemexp/templates/selectbox.html
chemexp-0.2.4.dist-info/LICENSE
chemexp-0.2.4.dist-info/METADATA
chemexp-0.2.4.dist-info/WHEEL
chemexp-0.2.4.dist-info/top_level.txt
chemexp-0.2.4.dist-info/RECORD
