Metadata-Version: 2.1
Name: chemexp
Version: 0.2.4
Summary: An explainer for Chemprop based on LIME and PathExplain.
Home-page: https://github.com/Locust2520/chemexp
Author: Fabien BERNIER
Author-email: fabien.bernier@telecomnancy.net
License: UNKNOWN
Keywords: explainer,explanation,visualization,chemprop,molecule,model,deep learning,graph
Platform: UNKNOWN
Classifier: Programming Language :: Python :: 3
Classifier: Programming Language :: Python :: 3.8
License-File: LICENSE
